{
  "countries": {
    "6813b6d446e731854c7ac79a": {
      "combat_ratio": 81.82,
      "combat_resets": 0,
      "eco_resets": 0,
      "history": [
        {
          "combat_ratio": 81.4,
          "new_resets": 0,
          "resetter_combat_ratio": null,
          "ts": "2026-05-19T10:53:00.828380+00:00"
        },
        {
          "combat_ratio": 81.4,
          "new_resets": 1,
          "resetter_combat_ratio": 91.3,
          "ts": "2026-05-20T10:41:03.855487+00:00"
        },
        {
          "combat_ratio": 81.4,
          "new_resets": 0,
          "resetter_combat_ratio": null,
          "ts": "2026-05-21T10:57:47.667268+00:00"
        },
        {
          "combat_ratio": 81.82,
          "new_resets": 1,
          "resetter_combat_ratio": 94.87,
          "ts": "2026-05-22T10:41:13.501310+00:00"
        },
        {
          "combat_ratio": 81.82,
          "new_resets": 0,
          "resetter_combat_ratio": null,
          "ts": "2026-05-23T09:42:45.900730+00:00"
        }
      ],
      "known_veterans": [
        "68c71c6108f0a4e094b64cd1",
        "68a217c477dbbe3211da0c87",
        "69036187009657975ceb4e37",
        "69033e9c6993cc1212858b2f",
        "6916e072991d93d5d34deedb",
        "6919c7be99b6f95d037a8087",
        "69065e23e8e12c3b9ff9f06b",
        "68fb92ae8831416ea7684f80",
        "68fb697597f7a72934bf3bc5",
        "690510343968fc6faf89a856",
        "690631da4284de8e5e898eff",
        "6906aa93d65e59eb3ba1a26e",
        "69025adcfe0f15858fead462",
        "6902032f582da7f4b18f5902",
        "68ff70b2ddd6dbcaaf468fc7",
        "6914918a0b5348273322d176",
        "69064cbcf4d83281b2b9974a",
        "691756e6b6d7886e8cd3bbf3",
        "6914b82c9aee34224001f473",
        "69418fc777214006429fdbbb",
        "69035220d2b4a4bcee5f396a",
        "6945bd36a3e161cb35b91c52",
        "6945bab3ecf9f19d2f3c17f8",
        "6945a97f91014485e27161bf",
        "69473a49955d216659cb3dc6"
      ],
      "last_creep_alert": null,
      "last_creep_delta": null,
      "last_demob_alert": null,
      "last_demob_delta": null,
      "last_discovery": "2026-05-18T12:44:56.790190+00:00",
      "last_flagged_at": null,
      "last_flagged_peak_ratio": null,
      "last_urgent_alert": null,
      "last_urgent_count": null,
      "name": "France",
      "new_resets": 0,
      "resetter_combat_ratio": null,
      "sample_size": 25,
      "user_resets": {
        "68c71c6108f0a4e094b64cd1": "2026-04-15T10:31:35.355Z",
        "68fb697597f7a72934bf3bc5": "2026-05-02T16:43:55.732Z",
        "68fb92ae8831416ea7684f80": "2026-05-04T20:00:41.096Z",
        "68ff70b2ddd6dbcaaf468fc7": "2026-05-17T13:20:31.944Z",
        "6902032f582da7f4b18f5902": "2026-05-21T11:50:23.785Z",
        "69025adcfe0f15858fead462": "2026-05-08T16:35:57.567Z",
        "69033e9c6993cc1212858b2f": "2026-05-13T11:07:18.195Z",
        "69035220d2b4a4bcee5f396a": "2026-04-29T09:48:05.096Z",
        "69036187009657975ceb4e37": "2026-05-17T10:04:43.196Z",
        "690510343968fc6faf89a856": "2026-05-03T12:45:08.100Z",
        "69064cbcf4d83281b2b9974a": "2026-04-26T10:09:48.175Z",
        "69065e23e8e12c3b9ff9f06b": "2026-05-19T21:55:52.586Z",
        "6906aa93d65e59eb3ba1a26e": "2026-05-11T14:12:13.231Z",
        "6914918a0b5348273322d176": "2026-05-04T12:08:22.690Z",
        "6914b82c9aee34224001f473": "2026-05-08T15:25:42.471Z",
        "6916e072991d93d5d34deedb": "2026-04-15T19:45:37.288Z",
        "691756e6b6d7886e8cd3bbf3": "2026-04-23T21:31:29.884Z",
        "6919c7be99b6f95d037a8087": "2026-04-07T18:56:25.606Z",
        "6945a97f91014485e27161bf": "2026-05-12T09:40:26.870Z",
        "6945bd36a3e161cb35b91c52": "2026-04-24T13:38:18.151Z",
        "69473a49955d216659cb3dc6": "2026-04-25T12:31:15.637Z"
      }
    },
    "6813b6d446e731854c7ac79c": {
      "combat_ratio": 27.27,
      "combat_resets": 0,
      "eco_resets": 0,
      "history": [
        {
          "combat_ratio": 20.0,
          "new_resets": 0,
          "resetter_combat_ratio": null,
          "ts": "2026-05-19T10:53:00.828380+00:00"
        },
        {
          "combat_ratio": 22.73,
          "new_resets": 1,
          "resetter_combat_ratio": 87.5,
          "ts": "2026-05-20T10:41:03.855487+00:00"
        },
        {
          "combat_ratio": 31.58,
          "new_resets": 1,
          "resetter_combat_ratio": 78.79,
          "ts": "2026-05-22T10:41:13.501310+00:00"
        },
        {
          "combat_ratio": 27.27,
          "new_resets": 1,
          "resetter_combat_ratio": 21.74,
          "ts": "2026-05-23T09:42:45.900730+00:00"
        }
      ],
      "known_veterans": [
        "69d003e252e32e997e209c3a",
        "69cfe4ee88769f2d03b75791",
        "69cecc587a0f47793a494591",
        "69ccde9f1a1f9166480a8b26",
        "69cebf8eeeda45a4b229def4",
        "69cd6685b45239c34ecaa21e",
        "69ccb9528c83b81ca7c91e2c",
        "69ccf81dbfeed1046d54ade3",
        "69cd85e74d309d4fc73fdfed",
        "69ce2b50b3a3e5e7791e0be1",
        "69cfeb2d5e2e9eebd04b7be0",
        "69ceebe870c6e3021dd7e934",
        "69d143acb9056ee8e15a184a",
        "69cd6513eb7905eef4fbdc3a",
        "69ceefd71a5e7b2eb9181868",
        "69cebfb898f354297b64528a",
        "69cd4d3ce7779e060d6ea3e3",
        "69cce0819a3777d39163464d",
        "69ce64a7c15043c1af20028c",
        "69cecb5069020a37689d6d46",
        "69d9685d5f926a2a3ff27487",
        "69d9684d0fda012adad24a49",
        "69d94b94a00c0386d76414b8",
        "69d8a70d0fda012ada707fea",
        "69d9511e2498137450263c51"
      ],
      "last_creep_alert": null,
      "last_creep_delta": null,
      "last_demob_alert": null,
      "last_demob_delta": null,
      "last_discovery": "2026-05-18T12:44:56.790190+00:00",
      "last_flagged_at": null,
      "last_flagged_peak_ratio": null,
      "last_urgent_alert": null,
      "last_urgent_count": null,
      "name": "Germany",
      "new_resets": 1,
      "resetter_combat_ratio": 21.74,
      "sample_size": 25,
      "user_resets": {
        "69ccb9528c83b81ca7c91e2c": "2026-04-09T05:27:08.870Z",
        "69ccde9f1a1f9166480a8b26": "2026-05-16T14:24:25.364Z",
        "69cce0819a3777d39163464d": "2026-05-12T11:58:09.776Z",
        "69ccf81dbfeed1046d54ade3": "2026-04-13T09:42:58.588Z",
        "69cd4d3ce7779e060d6ea3e3": "2026-04-01T17:43:22.148Z",
        "69cd6513eb7905eef4fbdc3a": "2026-05-17T13:59:05.476Z",
        "69cd6685b45239c34ecaa21e": "2026-05-22T20:18:35.877Z",
        "69cd85e74d309d4fc73fdfed": "2026-05-17T23:31:27.320Z",
        "69ce2b50b3a3e5e7791e0be1": "2026-05-17T21:12:24.030Z",
        "69ce64a7c15043c1af20028c": "2026-04-15T21:57:09.400Z",
        "69cebf8eeeda45a4b229def4": "2026-05-10T01:24:40.377Z",
        "69cecb5069020a37689d6d46": "2026-05-18T10:48:52.797Z",
        "69cecc587a0f47793a494591": "2026-05-22T10:33:05.671Z",
        "69ceebe870c6e3021dd7e934": "2026-04-26T23:01:04.005Z",
        "69ceefd71a5e7b2eb9181868": "2026-04-08T17:45:20.908Z",
        "69cfe4ee88769f2d03b75791": "2026-05-19T19:15:46.987Z",
        "69cfeb2d5e2e9eebd04b7be0": "2026-04-20T03:42:44.266Z",
        "69d003e252e32e997e209c3a": "2026-04-04T16:26:37.194Z",
        "69d143acb9056ee8e15a184a": "2026-05-01T14:08:28.626Z",
        "69d8a70d0fda012ada707fea": "2026-05-12T07:47:30.445Z",
        "69d94b94a00c0386d76414b8": "2026-05-13T06:12:40.482Z",
        "69d9684d0fda012adad24a49": "2026-05-15T15:55:54.193Z",
        "69d9685d5f926a2a3ff27487": "2026-05-16T08:45:06.143Z"
      }
    },
    "6813b6d446e731854c7ac79e": {
      "combat_ratio": 46.51,
      "combat_resets": 0,
      "eco_resets": 0,
      "history": [
        {
          "combat_ratio": 44.83,
          "new_resets": 0,
          "resetter_combat_ratio": null,
          "ts": "2026-05-19T10:53:00.828380+00:00"
        },
        {
          "combat_ratio": 46.51,
          "new_resets": 2,
          "resetter_combat_ratio": 75.05,
          "ts": "2026-05-20T10:41:03.855487+00:00"
        },
        {
          "combat_ratio": 46.51,
          "new_resets": 0,
          "resetter_combat_ratio": null,
          "ts": "2026-05-21T10:57:47.667268+00:00"
        },
        {
          "combat_ratio": 46.51,
          "new_resets": 1,
          "resetter_combat_ratio": 34.38,
          "ts": "2026-05-22T10:41:13.501310+00:00"
        },
        {
          "combat_ratio": 46.51,
          "new_resets": 1,
          "resetter_combat_ratio": 0.0,
          "ts": "2026-05-23T09:42:45.900730+00:00"
        }
      ],
      "known_veterans": [
        "6882a786c91f768fd3f7278b",
        "685d86e6a4eebc64d9f8f725",
        "6882b2708ed720aa964cc170",
        "6877853f521cb9c19b60aeaa",
        "690529e201185a7932ddf7fe",
        "6842843ed0e381ccda5746ec",
        "688c4737005bc031f0a1d4a7",
        "6910ac5675802288140ff70c",
        "694b1681c7c907fff5ba6dff",
        "6960e90acc472666cb90b5f6",
        "6973bb37eed64c805d5a1b33",
        "6981be6d7922e416bbc8c9a1",
        "698b1bd56bc7e7077d59eed8",
        "698ded23e105f15cf06b5fbe",
        "699de261b19b2c5fe3a4b444",
        "69a1a3c5ce3fdbcd3b008d1c",
        "69a388a0e65e0d2bf921dbc0",
        "691a593f45ce8539d0a4b55f",
        "6918d931cc751d7f456c36a3",
        "69b088efc5949dae6bf44614",
        "69b3df194b0d180f67dde54d",
        "69ad99b9618b3d609ef25ff7",
        "69b0542ab5486e4fd9f3cbc6",
        "699ec1a75a538fc336b42ebb",
        "69b1c3d0c5949dae6b55fdcc"
      ],
      "last_creep_alert": null,
      "last_creep_delta": null,
      "last_demob_alert": null,
      "last_demob_delta": null,
      "last_discovery": "2026-05-18T12:44:56.790190+00:00",
      "last_flagged_at": null,
      "last_flagged_peak_ratio": null,
      "last_urgent_alert": null,
      "last_urgent_count": null,
      "name": "United Kingdom",
      "new_resets": 1,
      "resetter_combat_ratio": 0.0,
      "sample_size": 25,
      "user_resets": {
        "685d86e6a4eebc64d9f8f725": "2026-05-17T13:22:51.890Z",
        "6877853f521cb9c19b60aeaa": "2026-05-19T19:03:50.901Z",
        "6882a786c91f768fd3f7278b": "2026-04-18T13:28:56.393Z",
        "688c4737005bc031f0a1d4a7": "2026-05-18T16:33:21.386Z",
        "690529e201185a7932ddf7fe": "2026-05-19T06:24:17.053Z",
        "6910ac5675802288140ff70c": "2026-04-18T06:13:04.672Z",
        "691a593f45ce8539d0a4b55f": "2026-04-30T06:57:21.294Z",
        "694b1681c7c907fff5ba6dff": "2026-05-19T16:04:58.290Z",
        "6960e90acc472666cb90b5f6": "2026-05-21T20:51:44.243Z",
        "6981be6d7922e416bbc8c9a1": "2026-05-22T15:48:15.415Z",
        "698b1bd56bc7e7077d59eed8": "2026-05-03T08:46:10.359Z",
        "698ded23e105f15cf06b5fbe": "2026-04-23T09:17:08.944Z",
        "699de261b19b2c5fe3a4b444": "2026-05-09T08:36:20.192Z",
        "69a1a3c5ce3fdbcd3b008d1c": "2026-04-28T19:16:03.874Z",
        "69a388a0e65e0d2bf921dbc0": "2026-04-17T21:21:15.516Z",
        "69ad99b9618b3d609ef25ff7": "2026-04-17T21:18:03.621Z",
        "69b0542ab5486e4fd9f3cbc6": "2026-05-20T14:18:42.759Z",
        "69b088efc5949dae6bf44614": "2026-04-22T20:17:06.214Z",
        "69b3df194b0d180f67dde54d": "2026-05-18T16:48:16.006Z"
      }
    },
    "6813b6d446e731854c7ac7a0": {
      "combat_ratio": 28.0,
      "combat_resets": 0,
      "eco_resets": 0,
      "history": [
        {
          "combat_ratio": 20.0,
          "new_resets": 0,
          "resetter_combat_ratio": null,
          "ts": "2026-05-19T10:53:00.828380+00:00"
        },
        {
          "combat_ratio": 20.0,
          "new_resets": 0,
          "resetter_combat_ratio": null,
          "ts": "2026-05-20T10:41:03.855487+00:00"
        },
        {
          "combat_ratio": 29.17,
          "new_resets": 1,
          "resetter_combat_ratio": 71.88,
          "ts": "2026-05-21T10:57:47.667268+00:00"
        },
        {
          "combat_ratio": 29.17,
          "new_resets": 0,
          "resetter_combat_ratio": null,
          "ts": "2026-05-22T10:41:13.501310+00:00"
        },
        {
          "combat_ratio": 36.0,
          "new_resets": 1,
          "resetter_combat_ratio": 82.35,
          "ts": "2026-05-23T09:42:45.900730+00:00"
        },
        {
          "combat_ratio": 36.0,
          "new_resets": 0,
          "resetter_combat_ratio": null,
          "ts": "2026-05-24T09:46:58.727404+00:00"
        },
        {
          "combat_ratio": 34.62,
          "new_resets": 1,
          "resetter_combat_ratio": 14.29,
          "ts": "2026-05-25T11:41:51.179590+00:00"
        },
        {
          "combat_ratio": 28.0,
          "combat_resets": 0,
          "eco_resets": 0,
          "new_resets": 0,
          "resetter_combat_ratio": null,
          "ts": "2026-05-25T19:47:24.866422+00:00"
        },
        {
          "combat_ratio": 28.0,
          "combat_resets": 0,
          "eco_resets": 0,
          "new_resets": 0,
          "resetter_combat_ratio": null,
          "ts": "2026-05-25T20:25:27.342961+00:00"
        },
        {
          "combat_ratio": 28.0,
          "combat_resets": 0,
          "eco_resets": 0,
          "new_resets": 0,
          "resetter_combat_ratio": null,
          "ts": "2026-05-25T20:43:54.257477+00:00"
        }
      ],
      "known_veterans": [
        "69b555f43af735a9906c6486",
        "69b3c280e86aeacd8ca4a7c5",
        "69b3b708c5949dae6b26eb6d",
        "69b46e1bb052a4f2e20ece7a",
        "69b468aa35541608f4449c5c",
        "69b3b26644d82934405e9773",
        "69bf0f5f0e1980dd1b8e89a5",
        "69bd3ccd2b3745eea5601700",
        "69bc3c6a84bbfcaa685c1e38",
        "69bd34221348cf457e66629d",
        "69b5b0b5579ffbb5e4b27072",
        "69b7d116e94a969626b516f2",
        "69b4ad6e6eeec30d5962d00f",
        "69baadacf25874079e9f24d0",
        "69c2b64092baf8f0c3dfd521",
        "69bcd2f22b5e4e5665f6ba17",
        "69c12676ab2d54d20d2ace74",
        "69c2e6575f22681ea534e7b4",
        "69be6148b036912afac6ae38",
        "69bea7d4dcbd31be3aca1b98",
        "69b53ff8d8430ef797b74a56",
        "69ba792a08ebed11edf989cf",
        "69ceb7d7b3a3e5e779a99245",
        "69cc4198c6be9203a3bb43ad",
        "69cec0ef476990332b9fc69e"
      ],
      "last_creep_alert": null,
      "last_creep_delta": null,
      "last_demob_alert": null,
      "last_demob_delta": null,
      "last_discovery": "2026-05-25T19:47:24.866422+00:00",
      "last_flagged_at": null,
      "last_flagged_peak_ratio": null,
      "last_urgent_alert": null,
      "last_urgent_count": null,
      "name": "Netherlands",
      "new_resets": 0,
      "resetter_combat_ratio": null,
      "sample_size": 25,
      "user_resets": {
        "69b3b26644d82934405e9773": "2026-05-18T18:34:56.902Z",
        "69b3b708c5949dae6b26eb6d": "2026-05-22T14:57:03.399Z",
        "69b3c280e86aeacd8ca4a7c5": "2026-05-24T10:16:51.273Z",
        "69b468aa35541608f4449c5c": "2026-05-10T19:52:19.337Z",
        "69b46e1bb052a4f2e20ece7a": "2026-05-22T12:43:00.547Z",
        "69b53ff8d8430ef797b74a56": "2026-04-23T12:50:26.489Z",
        "69b555f43af735a9906c6486": "2026-05-17T10:08:45.052Z",
        "69b5b0b5579ffbb5e4b27072": "2026-05-04T06:56:23.719Z",
        "69b7d116e94a969626b516f2": "2026-05-15T08:27:39.802Z",
        "69ba792a08ebed11edf989cf": "2026-04-09T09:09:23.201Z",
        "69baadacf25874079e9f24d0": "2026-05-17T11:39:56.124Z",
        "69bc3c6a84bbfcaa685c1e38": "2026-05-14T11:50:15.800Z",
        "69bd34221348cf457e66629d": "2026-05-18T14:50:00.161Z",
        "69bd3ccd2b3745eea5601700": "2026-05-02T06:44:58.620Z",
        "69bea7d4dcbd31be3aca1b98": "2026-04-09T17:26:35.609Z",
        "69bf0f5f0e1980dd1b8e89a5": "2026-04-28T04:29:41.738Z",
        "69c12676ab2d54d20d2ace74": "2026-05-24T13:48:52.333Z",
        "69c2e6575f22681ea534e7b4": "2026-05-10T08:12:19.730Z",
        "69cc4198c6be9203a3bb43ad": "2026-05-16T16:39:49.246Z",
        "69cec0ef476990332b9fc69e": "2026-05-06T08:21:34.633Z"
      }
    },
    "6813b6d446e731854c7ac7a2": {
      "combat_ratio": 40.91,
      "combat_resets": 0,
      "eco_resets": 0,
      "history": [
        {
          "combat_ratio": 40.91,
          "new_resets": 0,
          "resetter_combat_ratio": null,
          "ts": "2026-05-23T09:42:45.900730+00:00"
        },
        {
          "combat_ratio": 40.91,
          "new_resets": 1,
          "resetter_combat_ratio": 0.0,
          "ts": "2026-05-24T09:46:58.727404+00:00"
        },
        {
          "combat_ratio": 40.91,
          "new_resets": 0,
          "resetter_combat_ratio": null,
          "ts": "2026-05-25T11:41:51.179590+00:00"
        },
        {
          "combat_ratio": 40.91,
          "combat_resets": 0,
          "eco_resets": 0,
          "new_resets": 0,
          "resetter_combat_ratio": null,
          "ts": "2026-05-25T19:47:24.866422+00:00"
        },
        {
          "combat_ratio": 40.91,
          "combat_resets": 0,
          "eco_resets": 0,
          "new_resets": 0,
          "resetter_combat_ratio": null,
          "ts": "2026-05-25T20:25:27.342961+00:00"
        },
        {
          "combat_ratio": 40.91,
          "combat_resets": 0,
          "eco_resets": 0,
          "new_resets": 0,
          "resetter_combat_ratio": null,
          "ts": "2026-05-25T20:43:54.257477+00:00"
        }
      ],
      "known_veterans": [
        "69d2ac1243a67adf4e024b7b",
        "69d4ed54bc0ec32a4a42436d",
        "69d55e0f6b595becbf853d79",
        "69d7db33f7cc0387ad133431",
        "69d54b733535a2f5c59c2969",
        "69d3e6246341955760244029",
        "69d4e1d011bec0196ea8ecb9",
        "69d38c1843a5ff07f43d5da6",
        "69d4dd1c70ab5601d0eb54d9",
        "69d48aab60c7189005eaa325",
        "69d2ed249f38d300d59a2af1",
        "69d2deee43a5ff07f4e38ecf",
        "69d413fd9eefccc642122c94",
        "69d345fb9a1984dba5e7aa74",
        "69d390f1a6974fd542504690",
        "69d2f03c1affba41e16fc6cd",
        "69d3bf008137730fe4345d1e",
        "69d29f932813ceeb9b6456a9",
        "69d2cf922813ceeb9bbe9552",
        "69d27621f7ff62dda5ce6824",
        "69dadb33e86a67f8f63a2672",
        "69dbcf67f8d47c04e5d4582f",
        "69dd649422f5623f08d5d8e6",
        "69dd6ef7af97b01a97fbbfaa",
        "69de381eaf97b01a97859a74"
      ],
      "last_creep_alert": null,
      "last_creep_delta": null,
      "last_demob_alert": null,
      "last_demob_delta": null,
      "last_discovery": "2026-05-23T09:42:45.900730+00:00",
      "last_flagged_at": null,
      "last_flagged_peak_ratio": null,
      "last_urgent_alert": null,
      "last_urgent_count": null,
      "name": "Italy",
      "new_resets": 0,
      "resetter_combat_ratio": null,
      "sample_size": 25,
      "user_resets": {
        "69d27621f7ff62dda5ce6824": "2026-05-19T11:02:05.043Z",
        "69d29f932813ceeb9b6456a9": "2026-05-14T11:11:30.771Z",
        "69d2ac1243a67adf4e024b7b": "2026-05-17T08:42:46.664Z",
        "69d2deee43a5ff07f4e38ecf": "2026-05-11T20:53:43.955Z",
        "69d2ed249f38d300d59a2af1": "2026-05-15T13:43:05.385Z",
        "69d2f03c1affba41e16fc6cd": "2026-05-22T16:43:54.806Z",
        "69d345fb9a1984dba5e7aa74": "2026-05-19T14:10:24.881Z",
        "69d38c1843a5ff07f43d5da6": "2026-04-10T10:46:14.292Z",
        "69d390f1a6974fd542504690": "2026-05-19T14:39:04.779Z",
        "69d3bf008137730fe4345d1e": "2026-05-19T16:57:16.648Z",
        "69d3e6246341955760244029": "2026-05-19T14:48:57.196Z",
        "69d413fd9eefccc642122c94": "2026-05-18T20:02:02.796Z",
        "69d48aab60c7189005eaa325": "2026-05-20T20:58:40.486Z",
        "69d4dd1c70ab5601d0eb54d9": "2026-05-23T13:09:32.923Z",
        "69d4e1d011bec0196ea8ecb9": "2026-04-08T21:40:22.692Z",
        "69d54b733535a2f5c59c2969": "2026-04-09T10:57:27.323Z",
        "69dadb33e86a67f8f63a2672": "2026-04-19T01:36:58.968Z",
        "69dbcf67f8d47c04e5d4582f": "2026-04-19T21:40:15.933Z",
        "69dd6ef7af97b01a97fbbfaa": "2026-04-15T10:40:03.730Z",
        "69de381eaf97b01a97859a74": "2026-04-17T13:34:58.062Z"
      }
    },
    "6813b6d446e731854c7ac7a4": {
      "combat_ratio": 53.33,
      "combat_resets": 0,
      "eco_resets": 0,
      "history": [
        {
          "combat_ratio": 46.15,
          "new_resets": 0,
          "resetter_combat_ratio": null,
          "ts": "2026-05-19T10:53:00.828380+00:00"
        },
        {
          "combat_ratio": 53.33,
          "new_resets": 0,
          "resetter_combat_ratio": null,
          "ts": "2026-05-20T10:41:03.855487+00:00"
        },
        {
          "combat_ratio": 53.33,
          "new_resets": 0,
          "resetter_combat_ratio": null,
          "ts": "2026-05-21T10:57:47.667268+00:00"
        },
        {
          "combat_ratio": 53.33,
          "new_resets": 1,
          "resetter_combat_ratio": 11.76,
          "ts": "2026-05-22T10:41:13.501310+00:00"
        },
        {
          "combat_ratio": 53.33,
          "new_resets": 0,
          "resetter_combat_ratio": null,
          "ts": "2026-05-23T09:42:45.900730+00:00"
        },
        {
          "combat_ratio": 53.33,
          "new_resets": 0,
          "resetter_combat_ratio": null,
          "ts": "2026-05-24T09:46:58.727404+00:00"
        },
        {
          "combat_ratio": 53.33,
          "new_resets": 0,
          "resetter_combat_ratio": null,
          "ts": "2026-05-25T11:41:51.179590+00:00"
        },
        {
          "combat_ratio": 53.33,
          "combat_resets": 0,
          "eco_resets": 0,
          "new_resets": 0,
          "resetter_combat_ratio": null,
          "ts": "2026-05-25T19:47:24.866422+00:00"
        },
        {
          "combat_ratio": 53.33,
          "combat_resets": 0,
          "eco_resets": 0,
          "new_resets": 0,
          "resetter_combat_ratio": null,
          "ts": "2026-05-25T20:25:27.342961+00:00"
        },
        {
          "combat_ratio": 53.33,
          "combat_resets": 0,
          "eco_resets": 0,
          "new_resets": 0,
          "resetter_combat_ratio": null,
          "ts": "2026-05-25T20:43:54.257477+00:00"
        }
      ],
      "known_veterans": [
        "69b2a698a583a3b5f9567890",
        "69b03d1b4a0b814a34e06e9a",
        "69b41ca244d8293440241af1",
        "69b0aedccbf2b5c108e339a1",
        "69b310c919f98f6ceba5b93e",
        "69bc678d0f50f6f334a3c4aa",
        "69ba42913f756b6d59c124e2",
        "69b7bf95ca9a42b7ef66b7de",
        "69b492545f34cb744fd46517",
        "69b73e37805a5bf5ae2b2bdc",
        "69b311efcbf2b5c108a623af",
        "69b480b421a9ed4b968a4a40",
        "69b323877972e334e3bd22da",
        "69c4dc19cde5836cb7979931",
        "69b85514c0dd19d33218e8d4",
        "69c1b1f7585318550a94c71b",
        "69b29bce2895f070b7e6fe90",
        "69c65cfcc1a06d6b1e74ecfd",
        "69cfd1565752aefa8b3caaca",
        "69caa9edb37e0eb78f499cff",
        "69b46b4bb34bca57fd13eba1",
        "69d7ec8324981374504dd728",
        "69d8c35f3553eff9bdbe964f",
        "69d52703216f0b15398005ac",
        "69da360ed11e8da853d42d0c"
      ],
      "last_creep_alert": null,
      "last_creep_delta": null,
      "last_demob_alert": null,
      "last_demob_delta": null,
      "last_discovery": "2026-05-25T19:47:24.866422+00:00",
      "last_flagged_at": null,
      "last_flagged_peak_ratio": null,
      "last_urgent_alert": null,
      "last_urgent_count": null,
      "name": "Belgium",
      "new_resets": 0,
      "resetter_combat_ratio": null,
      "sample_size": 25,
      "user_resets": {
        "69b0aedccbf2b5c108e339a1": "2026-04-23T22:27:16.982Z",
        "69b29bce2895f070b7e6fe90": "2026-04-27T06:40:26.119Z",
        "69b2a698a583a3b5f9567890": "2026-05-17T07:38:04.928Z",
        "69b311efcbf2b5c108a623af": "2026-05-18T11:52:13.684Z",
        "69b323877972e334e3bd22da": "2026-05-19T08:07:48.698Z",
        "69b41ca244d8293440241af1": "2026-05-16T22:00:00.775Z",
        "69b46b4bb34bca57fd13eba1": "2026-05-17T15:15:54.662Z",
        "69b492545f34cb744fd46517": "2026-05-17T17:38:47.472Z",
        "69b73e37805a5bf5ae2b2bdc": "2026-05-11T08:12:36.932Z",
        "69b7bf95ca9a42b7ef66b7de": "2026-05-10T17:33:10.444Z",
        "69b85514c0dd19d33218e8d4": "2026-04-28T19:53:17.633Z",
        "69ba42913f756b6d59c124e2": "2026-05-18T02:05:50.489Z",
        "69bc678d0f50f6f334a3c4aa": "2026-05-22T07:15:04.393Z",
        "69c1b1f7585318550a94c71b": "2026-05-18T20:03:23.529Z",
        "69c4dc19cde5836cb7979931": "2026-05-10T06:09:14.941Z",
        "69c65cfcc1a06d6b1e74ecfd": "2026-05-13T12:17:18.029Z",
        "69caa9edb37e0eb78f499cff": "2026-05-15T07:18:53.525Z",
        "69d52703216f0b15398005ac": "2026-04-25T19:56:59.245Z",
        "69d7ec8324981374504dd728": "2026-04-16T13:15:46.042Z",
        "69d8c35f3553eff9bdbe964f": "2026-04-18T19:49:59.167Z"
      }
    },
    "6813b6d446e731854c7ac7aa": {
      "combat_ratio": 4.76,
      "combat_resets": 0,
      "eco_resets": 0,
      "known_veterans": [
        "6919a2eb45ce8539d0500fe4",
        "6918c782c6bbe2053f795626",
        "68f5063db7bd4d5177772040",
        "691df08dc6bbe2053fe5e334",
        "6904e98375ad2efaf776bae8",
        "6970b6bb58b9cb99aa54e974",
        "6971fd57cb5a8a5462b6ed78",
        "696d3017a7694f38eb709571",
        "696bdb89d304116ae14859ad",
        "698254af51756dc63315df49",
        "696d381177fed94300fac03b",
        "6994704fa95c454990aa5aba",
        "6995b1356d4c5be819b7bc33",
        "6993b5561b6ba9909c5b256e",
        "6993a425cd957d3e93a9f2ad",
        "6982b557e475769834b5569f",
        "699b4302986493176029790f",
        "69977d422dc9b74ec4681b0b",
        "69959a32e855fe967af42dd4",
        "6990a44d6488201809bdc6dd",
        "696c18ce702d93d9d5f68dd5",
        "6996f9f696787ce84baa6257",
        "699915d9d87267cb1d85456d",
        "697ea0199271365e8a85e15d",
        "69ade91592668a04c70c6a31"
      ],
      "last_creep_alert": null,
      "last_creep_delta": null,
      "last_demob_alert": null,
      "last_demob_delta": null,
      "last_discovery": "2026-05-18T12:44:56.790190+00:00",
      "last_flagged_at": null,
      "last_flagged_peak_ratio": null,
      "last_urgent_alert": null,
      "last_urgent_count": null,
      "name": "Portugal",
      "sample_size": 25,
      "user_resets": {}
    },
    "6813b6d446e731854c7ac7b8": {
      "combat_ratio": 88.89,
      "combat_resets": 0,
      "eco_resets": 0,
      "history": [
        {
          "combat_ratio": 89.8,
          "new_resets": 0,
          "resetter_combat_ratio": null,
          "ts": "2026-05-24T09:46:58.727404+00:00"
        },
        {
          "combat_ratio": 88.89,
          "new_resets": 1,
          "resetter_combat_ratio": 0.0,
          "ts": "2026-05-25T11:41:51.179590+00:00"
        },
        {
          "combat_ratio": 88.89,
          "combat_resets": 0,
          "eco_resets": 0,
          "new_resets": 0,
          "resetter_combat_ratio": null,
          "ts": "2026-05-25T19:47:24.866422+00:00"
        },
        {
          "combat_ratio": 88.89,
          "combat_resets": 0,
          "eco_resets": 0,
          "new_resets": 0,
          "resetter_combat_ratio": null,
          "ts": "2026-05-25T20:25:27.342961+00:00"
        },
        {
          "combat_ratio": 88.89,
          "combat_resets": 0,
          "eco_resets": 0,
          "new_resets": 0,
          "resetter_combat_ratio": null,
          "ts": "2026-05-25T20:43:54.257477+00:00"
        }
      ],
      "known_veterans": [
        "6829c71bf9fe6076b38a5379",
        "681a2f5b4c586e01fbcadba4",
        "68288dae95ff84572bfd0337",
        "6825c9bab490ccafd670a30c",
        "6829f52d8c06514dc2a36f74",
        "683083ff9a4536aed996e114",
        "681797320479a9ceb1902324",
        "682b241487f122ddeb4bacb6",
        "6878b87a002311c68a3f3c26",
        "6879d778820ed429e1825ffb",
        "68266beec517b26c38b8fb0a",
        "6878a9c67869eb193752b6d3",
        "6878987463ae472cc7fb4f4a",
        "6878bb286097872ea4cce521",
        "682b6bb3e65588148785878e",
        "6878f3592bdf9a42b590de26",
        "682f7ce98dff660fbf201ea6",
        "688c3e804f7299ac68496349",
        "688b4b2b87390e70c372f617",
        "68474da33194d84192e6d54c",
        "6846c91929ce4e2dd13868a5",
        "690b90816fdd2d7701fe85a8",
        "690e5a730786722cb81566d4",
        "690b1d5d5c3b907278d92d44",
        "6920d4c46021f881e24ed130"
      ],
      "last_creep_alert": null,
      "last_creep_delta": null,
      "last_demob_alert": null,
      "last_demob_delta": null,
      "last_discovery": "2026-05-24T09:46:58.727404+00:00",
      "last_flagged_at": null,
      "last_flagged_peak_ratio": null,
      "last_urgent_alert": null,
      "last_urgent_count": null,
      "name": "Lithuania",
      "new_resets": 0,
      "resetter_combat_ratio": null,
      "sample_size": 25,
      "user_resets": {
        "681a2f5b4c586e01fbcadba4": "2026-04-03T02:50:26.231Z",
        "6825c9bab490ccafd670a30c": "2026-04-08T08:10:21.030Z",
        "68266beec517b26c38b8fb0a": "2026-04-08T12:32:52.024Z",
        "68288dae95ff84572bfd0337": "2026-04-07T07:23:45.721Z",
        "6829c71bf9fe6076b38a5379": "2026-04-25T23:12:45.929Z",
        "6829f52d8c06514dc2a36f74": "2026-05-22T11:50:13.862Z",
        "682b241487f122ddeb4bacb6": "2026-05-23T07:17:28.291Z",
        "683083ff9a4536aed996e114": "2026-04-28T07:46:58.925Z",
        "6846c91929ce4e2dd13868a5": "2026-05-18T13:58:03.941Z",
        "68474da33194d84192e6d54c": "2026-05-20T05:12:27.484Z",
        "6878987463ae472cc7fb4f4a": "2026-05-16T19:16:26.061Z",
        "6878a9c67869eb193752b6d3": "2026-03-31T05:03:05.596Z",
        "6878b87a002311c68a3f3c26": "2026-05-19T20:47:59.586Z",
        "6878bb286097872ea4cce521": "2026-04-27T10:31:21.448Z",
        "6878f3592bdf9a42b590de26": "2026-05-20T09:00:02.457Z",
        "6879d778820ed429e1825ffb": "2026-05-21T18:07:01.786Z",
        "688b4b2b87390e70c372f617": "2026-05-13T18:40:23.376Z",
        "688c3e804f7299ac68496349": "2026-05-18T10:09:24.671Z",
        "690b1d5d5c3b907278d92d44": "2026-04-02T18:35:53.875Z",
        "690b90816fdd2d7701fe85a8": "2026-05-20T12:33:40.604Z",
        "690e5a730786722cb81566d4": "2026-05-20T10:16:26.737Z",
        "6920d4c46021f881e24ed130": "2026-05-24T16:35:27.340Z"
      }
    },
    "6813b6d446e731854c7ac7e5": {
      "combat_ratio": 0.0,
      "combat_resets": 0,
      "eco_resets": 0,
      "history": [
        {
          "combat_ratio": 15.38,
          "new_resets": 0,
          "resetter_combat_ratio": null,
          "ts": "2026-05-19T10:53:00.828380+00:00"
        },
        {
          "combat_ratio": 15.38,
          "new_resets": 1,
          "resetter_combat_ratio": 87.8,
          "ts": "2026-05-20T10:41:03.855487+00:00"
        },
        {
          "combat_ratio": 16.67,
          "new_resets": 0,
          "resetter_combat_ratio": null,
          "ts": "2026-05-21T10:57:47.667268+00:00"
        },
        {
          "combat_ratio": 15.38,
          "new_resets": 1,
          "resetter_combat_ratio": 0.0,
          "ts": "2026-05-22T10:41:13.501310+00:00"
        },
        {
          "combat_ratio": 15.38,
          "new_resets": 0,
          "resetter_combat_ratio": null,
          "ts": "2026-05-23T09:42:45.900730+00:00"
        },
        {
          "combat_ratio": 15.38,
          "new_resets": 0,
          "resetter_combat_ratio": null,
          "ts": "2026-05-24T09:46:58.727404+00:00"
        },
        {
          "combat_ratio": 15.38,
          "new_resets": 1,
          "resetter_combat_ratio": 0.0,
          "ts": "2026-05-25T11:41:51.179590+00:00"
        },
        {
          "combat_ratio": 0.0,
          "combat_resets": 0,
          "eco_resets": 1,
          "new_resets": 1,
          "resetter_combat_ratio": 0.0,
          "ts": "2026-05-25T19:47:24.866422+00:00"
        },
        {
          "combat_ratio": 0.0,
          "combat_resets": 0,
          "eco_resets": 0,
          "new_resets": 0,
          "resetter_combat_ratio": null,
          "ts": "2026-05-25T20:25:27.342961+00:00"
        },
        {
          "combat_ratio": 0.0,
          "combat_resets": 0,
          "eco_resets": 0,
          "new_resets": 0,
          "resetter_combat_ratio": null,
          "ts": "2026-05-25T20:43:54.257477+00:00"
        }
      ],
      "known_veterans": [
        "691c31c69317706a74ff84fe",
        "6912b18159d39d64afbbc4f0",
        "691a31f392948e91cb9d2334",
        "69619a809aa619cc592ea334",
        "6943c1cc980f402c92ce7879",
        "696d5777fe9d5e4fd70a652e",
        "6918b289cc751d7f455cb802",
        "696e0aef82ecc0f3cf5d509b",
        "695041f32b332672a6278aff",
        "6952f188acdca89d8619919a",
        "68f789b046ad5078319c5bbf",
        "68f5dd6a22a4934adae9e491",
        "692eeffccd4d5524651ce880",
        "69703b8eaadefa371703c72a",
        "69827a0e7cf831a523f54bd7",
        "6919be1bdb65494c1b26afa1",
        "696d1e537480b5635b033192",
        "6991461c6bb70e191fe7a395",
        "698de9b6f4652a0daac50ffa",
        "698c0ef6dd9e998685eb9270",
        "696b9c5ac9c4e2ee34af5bbf",
        "696ef0a491307f1d7ce7090a",
        "69a271f6ef10a1245a784c5a",
        "696a1e0ccd257554cd1950b9",
        "69b0017ca403356a8a908828"
      ],
      "last_creep_alert": null,
      "last_creep_delta": null,
      "last_demob_alert": null,
      "last_demob_delta": null,
      "last_discovery": "2026-05-25T19:47:24.866422+00:00",
      "last_flagged_at": null,
      "last_flagged_peak_ratio": null,
      "last_urgent_alert": null,
      "last_urgent_count": null,
      "name": "United States",
      "new_resets": 0,
      "resetter_combat_ratio": null,
      "sample_size": 25,
      "user_resets": {
        "68f789b046ad5078319c5bbf": "2026-04-24T03:12:55.410Z",
        "6912b18159d39d64afbbc4f0": "2026-05-05T23:37:26.601Z",
        "6919be1bdb65494c1b26afa1": "2026-04-01T00:55:11.874Z",
        "691a31f392948e91cb9d2334": "2026-05-09T11:56:33.134Z",
        "691c31c69317706a74ff84fe": "2026-04-27T05:45:44.264Z",
        "692eeffccd4d5524651ce880": "2026-04-26T01:50:08.207Z",
        "6943c1cc980f402c92ce7879": "2026-05-18T15:19:24.609Z",
        "695041f32b332672a6278aff": "2026-05-19T20:51:45.546Z",
        "6952f188acdca89d8619919a": "2026-04-23T10:52:27.293Z",
        "69619a809aa619cc592ea334": "2026-05-25T15:21:01.869Z",
        "696b9c5ac9c4e2ee34af5bbf": "2026-05-14T07:55:03.525Z",
        "696d1e537480b5635b033192": "2026-05-14T06:24:30.977Z",
        "696d5777fe9d5e4fd70a652e": "2026-04-18T15:12:52.751Z",
        "696e0aef82ecc0f3cf5d509b": "2026-05-17T15:25:40.486Z",
        "696ef0a491307f1d7ce7090a": "2026-05-22T12:48:05.145Z",
        "69703b8eaadefa371703c72a": "2026-05-13T02:06:04.280Z",
        "69827a0e7cf831a523f54bd7": "2026-05-20T04:31:04.710Z",
        "698c0ef6dd9e998685eb9270": "2026-04-26T06:14:13.160Z",
        "698de9b6f4652a0daac50ffa": "2026-05-09T13:55:55.800Z",
        "6991461c6bb70e191fe7a395": "2026-04-13T02:54:15.439Z",
        "69a271f6ef10a1245a784c5a": "2026-05-12T06:22:44.587Z",
        "69b0017ca403356a8a908828": "2026-04-28T04:57:22.252Z"
      }
    },
    "6813b6d446e731854c7ac7ef": {
      "combat_ratio": 52.31,
      "combat_resets": 0,
      "eco_resets": 0,
      "history": [
        {
          "combat_ratio": 41.48,
          "new_resets": 0,
          "resetter_combat_ratio": null,
          "ts": "2026-05-21T10:57:47.667268+00:00"
        },
        {
          "combat_ratio": 42.26,
          "new_resets": 0,
          "resetter_combat_ratio": null,
          "ts": "2026-05-22T10:41:13.501310+00:00"
        },
        {
          "combat_ratio": 42.26,
          "new_resets": 0,
          "resetter_combat_ratio": null,
          "ts": "2026-05-23T09:42:45.900730+00:00"
        },
        {
          "combat_ratio": 74.57,
          "new_resets": 1,
          "resetter_combat_ratio": 84.62,
          "ts": "2026-05-24T09:46:58.727404+00:00"
        },
        {
          "combat_ratio": 74.57,
          "new_resets": 0,
          "resetter_combat_ratio": null,
          "ts": "2026-05-25T11:41:51.179590+00:00"
        },
        {
          "combat_ratio": 52.31,
          "combat_resets": 0,
          "eco_resets": 1,
          "new_resets": 1,
          "resetter_combat_ratio": 0.0,
          "ts": "2026-05-25T19:47:24.866422+00:00"
        },
        {
          "combat_ratio": 52.31,
          "combat_resets": 0,
          "eco_resets": 0,
          "new_resets": 0,
          "resetter_combat_ratio": null,
          "ts": "2026-05-25T20:25:27.342961+00:00"
        },
        {
          "combat_ratio": 52.31,
          "combat_resets": 0,
          "eco_resets": 0,
          "new_resets": 0,
          "resetter_combat_ratio": null,
          "ts": "2026-05-25T20:43:54.257477+00:00"
        }
      ],
      "known_veterans": [
        "682883d106241b38def41fcd",
        "688d524efbe98e2b0dcfcb81",
        "695c6e3ffb75e9229fb7f417",
        "6955be14b1fc6d0b7bfde964",
        "6977a239ab7663db3ac03c5e",
        "69892fbcc5c82ef9aea416c3",
        "69bd149d1348cf457e2c64bb",
        "696b989e1eb1704c85ed0a30",
        "69c48d5e1bbe1908ba627f18",
        "69767e08d0b91ae6b45500bb"
      ],
      "last_creep_alert": null,
      "last_creep_delta": null,
      "last_demob_alert": null,
      "last_demob_delta": null,
      "last_discovery": "2026-05-21T10:57:47.667268+00:00",
      "last_flagged_at": null,
      "last_flagged_peak_ratio": null,
      "last_urgent_alert": null,
      "last_urgent_count": null,
      "name": "Denmark",
      "new_resets": 0,
      "resetter_combat_ratio": null,
      "sample_size": 10,
      "user_resets": {
        "682883d106241b38def41fcd": "2026-05-18T14:40:07.158Z",
        "688d524efbe98e2b0dcfcb81": "2026-05-18T20:31:57.613Z",
        "6955be14b1fc6d0b7bfde964": "2026-05-16T20:46:20.262Z",
        "695c6e3ffb75e9229fb7f417": "2026-05-20T04:05:10.526Z",
        "6977a239ab7663db3ac03c5e": "2026-05-13T21:29:01.576Z",
        "69892fbcc5c82ef9aea416c3": "2026-05-24T08:48:15.501Z",
        "69bd149d1348cf457e2c64bb": "2026-05-25T15:43:46.153Z",
        "69c48d5e1bbe1908ba627f18": "2026-05-21T06:37:11.918Z"
      }
    },
    "6813b6d446e731854c7ac7f2": {
      "combat_ratio": 84.38,
      "combat_resets": 0,
      "eco_resets": 0,
      "history": [
        {
          "combat_ratio": 84.38,
          "new_resets": 0,
          "resetter_combat_ratio": null,
          "ts": "2026-05-24T09:46:58.727404+00:00"
        }
      ],
      "known_veterans": [
        "69df88091da8142b69453e8e",
        "69df85d2af97b01a97db2f41",
        "69df82d81da8142b693c820f",
        "69df83ffa2a31c9a240c38f1",
        "69df82906aef50deba9f7ebc",
        "69df80e3c9e86925c5636862",
        "69df81eaa03070cad5665b75",
        "69df7e9a6416cd844877df84",
        "69df7c8e2862fd757aa715c0",
        "69df79980fb8f23528541f34",
        "69df77be8348a58fd772c3ee",
        "69df77bd405cba980f23c789",
        "69df78ed5bb1f1ef9f3d37a3",
        "69df7535ee3b630e26487a5e",
        "69df76250fb8f2352849f009",
        "69df765cbd0b3c07723d683a",
        "69df725fa42e300f963542f4",
        "69df72d01da8142b69271937",
        "69df6f476aef50deba87c8b4",
        "69df7108eb6a48b7f446413d",
        "69df6b97a03070cad539ad2d",
        "69df6ce65bb1f1ef9f33dc5c",
        "69df69a30e1f8588dc4d125b",
        "69df689286f55440dc50c0e5",
        "69df670fbd0b3c0772277379"
      ],
      "last_creep_alert": null,
      "last_creep_delta": null,
      "last_demob_alert": null,
      "last_demob_delta": null,
      "last_discovery": "2026-05-24T09:46:58.727404+00:00",
      "last_flagged_at": null,
      "last_flagged_peak_ratio": null,
      "last_urgent_alert": null,
      "last_urgent_count": null,
      "name": "Sweden",
      "new_resets": 0,
      "resetter_combat_ratio": null,
      "sample_size": 25,
      "user_resets": {
        "69df670fbd0b3c0772277379": "2026-05-18T11:16:09.000Z",
        "69df689286f55440dc50c0e5": "2026-05-19T10:59:05.898Z",
        "69df69a30e1f8588dc4d125b": "2026-04-17T08:20:05.733Z",
        "69df6ce65bb1f1ef9f33dc5c": "2026-05-19T13:30:28.517Z",
        "69df6f476aef50deba87c8b4": "2026-05-18T08:52:36.372Z",
        "69df7108eb6a48b7f446413d": "2026-05-19T12:05:51.282Z",
        "69df725fa42e300f963542f4": "2026-05-23T23:01:23.287Z",
        "69df72d01da8142b69271937": "2026-05-16T10:54:10.910Z",
        "69df76250fb8f2352849f009": "2026-05-23T07:15:47.700Z",
        "69df765cbd0b3c07723d683a": "2026-04-22T12:42:09.484Z",
        "69df77bd405cba980f23c789": "2026-05-19T07:41:18.786Z",
        "69df77be8348a58fd772c3ee": "2026-05-19T19:06:53.952Z",
        "69df78ed5bb1f1ef9f3d37a3": "2026-05-23T19:01:02.554Z",
        "69df79980fb8f23528541f34": "2026-04-16T12:42:36.255Z",
        "69df7c8e2862fd757aa715c0": "2026-05-22T06:24:10.681Z",
        "69df7e9a6416cd844877df84": "2026-05-23T19:23:19.169Z",
        "69df80e3c9e86925c5636862": "2026-05-19T17:52:13.353Z",
        "69df81eaa03070cad5665b75": "2026-05-24T06:07:41.353Z",
        "69df82906aef50deba9f7ebc": "2026-05-19T13:57:56.579Z",
        "69df82d81da8142b693c820f": "2026-04-15T18:44:16.217Z",
        "69df83ffa2a31c9a240c38f1": "2026-05-17T22:10:57.363Z",
        "69df88091da8142b69453e8e": "2026-04-16T21:17:54.856Z"
      }
    },
    "6813b6d446e731854c7ac802": {
      "combat_ratio": 69.81,
      "combat_resets": 0,
      "eco_resets": 0,
      "history": [
        {
          "combat_ratio": 0.0,
          "new_resets": 0,
          "resetter_combat_ratio": null,
          "ts": "2026-05-19T10:53:00.828380+00:00"
        },
        {
          "combat_ratio": 0.0,
          "new_resets": 0,
          "resetter_combat_ratio": null,
          "ts": "2026-05-20T10:41:03.855487+00:00"
        },
        {
          "combat_ratio": 18.18,
          "new_resets": 6,
          "resetter_combat_ratio": 89.19,
          "ts": "2026-05-21T10:57:47.667268+00:00"
        },
        {
          "combat_ratio": 71.79,
          "new_resets": 5,
          "resetter_combat_ratio": 85.42,
          "ts": "2026-05-22T10:41:13.501310+00:00"
        },
        {
          "combat_ratio": 71.79,
          "new_resets": 0,
          "resetter_combat_ratio": null,
          "ts": "2026-05-23T09:42:45.900730+00:00"
        },
        {
          "combat_ratio": 71.79,
          "new_resets": 0,
          "resetter_combat_ratio": null,
          "ts": "2026-05-24T09:46:58.727404+00:00"
        },
        {
          "combat_ratio": 71.79,
          "new_resets": 0,
          "resetter_combat_ratio": null,
          "ts": "2026-05-25T11:41:51.179590+00:00"
        },
        {
          "combat_ratio": 69.81,
          "combat_resets": 0,
          "eco_resets": 0,
          "new_resets": 0,
          "resetter_combat_ratio": null,
          "ts": "2026-05-25T19:47:24.866422+00:00"
        },
        {
          "combat_ratio": 69.81,
          "combat_resets": 0,
          "eco_resets": 0,
          "new_resets": 0,
          "resetter_combat_ratio": null,
          "ts": "2026-05-25T20:25:27.342961+00:00"
        },
        {
          "combat_ratio": 69.81,
          "combat_resets": 0,
          "eco_resets": 0,
          "new_resets": 0,
          "resetter_combat_ratio": null,
          "ts": "2026-05-25T20:43:54.257477+00:00"
        }
      ],
      "known_veterans": [
        "6813b773efecdf9bab196e72",
        "688e2575779d04817c1d08a6",
        "69760f1028393f2225b1010c",
        "69762ebf4bfbdc5ce917b38d",
        "6987b7e1ad2758110f11f580",
        "69879eabb0b2351dbe88454a",
        "6987b385537b1bf1e7606f98",
        "6987a31fcfa2ae928252af28",
        "6987b47da5d3382f28466950",
        "6987a0b62fb0bdcb9107935b",
        "6987a02ce0037f22c7284da9",
        "6987a98a2fb0bdcb9126ca65",
        "69a2ba05a8a3b031b7669b50",
        "69a16022acd5ab212e02aa50",
        "69a16370a5a565788e3b6d1e",
        "69a15d1b07b73de8faab1d9d",
        "69a15bb8b23c69f10005da66",
        "69a15b8f4d2abd93de8fe433",
        "69a15d2d07b73de8faabca98",
        "69a2d584a27535f584a4c21c",
        "69a15be98cf8b70e48249008",
        "69a17818f4a972e0fe739991",
        "69a5dd0e129837ecc9b3f9b1",
        "69a165e60ca0a7d5ff73533b",
        "69a16114ec91a7019f7c5cf5"
      ],
      "last_creep_alert": null,
      "last_creep_delta": null,
      "last_demob_alert": null,
      "last_demob_delta": null,
      "last_discovery": "2026-05-25T19:47:24.866422+00:00",
      "last_flagged_at": null,
      "last_flagged_peak_ratio": null,
      "last_urgent_alert": null,
      "last_urgent_count": null,
      "name": "Norway",
      "new_resets": 0,
      "resetter_combat_ratio": null,
      "sample_size": 25,
      "user_resets": {
        "688e2575779d04817c1d08a6": "2026-05-21T17:45:31.758Z",
        "69760f1028393f2225b1010c": "2026-05-06T18:40:41.898Z",
        "69762ebf4bfbdc5ce917b38d": "2026-05-15T22:03:34.960Z",
        "69879eabb0b2351dbe88454a": "2026-05-20T18:06:09.979Z",
        "6987a02ce0037f22c7284da9": "2026-05-02T21:46:45.272Z",
        "6987a0b62fb0bdcb9107935b": "2026-05-09T23:08:31.407Z",
        "6987a31fcfa2ae928252af28": "2026-05-20T11:14:46.361Z",
        "6987a98a2fb0bdcb9126ca65": "2026-05-20T19:05:48.003Z",
        "6987b385537b1bf1e7606f98": "2026-05-22T07:51:39.922Z",
        "6987b47da5d3382f28466950": "2026-05-22T06:35:59.878Z",
        "69a15b8f4d2abd93de8fe433": "2026-05-06T13:28:16.186Z",
        "69a15bb8b23c69f10005da66": "2026-05-01T11:00:52.567Z",
        "69a15be98cf8b70e48249008": "2026-05-22T04:14:47.714Z",
        "69a15d2d07b73de8faabca98": "2026-05-22T06:33:22.605Z",
        "69a16022acd5ab212e02aa50": "2026-05-21T01:42:55.347Z",
        "69a16114ec91a7019f7c5cf5": "2026-05-11T05:20:59.555Z",
        "69a16370a5a565788e3b6d1e": "2026-05-03T08:12:46.668Z",
        "69a165e60ca0a7d5ff73533b": "2026-05-20T17:17:30.363Z",
        "69a17818f4a972e0fe739991": "2026-05-06T12:33:11.638Z",
        "69a2ba05a8a3b031b7669b50": "2026-05-21T10:20:43.974Z",
        "69a2d584a27535f584a4c21c": "2026-05-10T16:39:15.541Z",
        "69a5dd0e129837ecc9b3f9b1": "2026-05-05T10:31:44.851Z"
      }
    },
    "6813b6d446e731854c7ac808": {
      "combat_ratio": 51.56,
      "combat_resets": 0,
      "eco_resets": 0,
      "history": [
        {
          "combat_ratio": 51.61,
          "new_resets": 0,
          "resetter_combat_ratio": null,
          "ts": "2026-05-19T10:53:00.828380+00:00"
        },
        {
          "combat_ratio": 51.61,
          "new_resets": 1,
          "resetter_combat_ratio": 0.0,
          "ts": "2026-05-20T10:41:03.855487+00:00"
        },
        {
          "combat_ratio": 61.54,
          "new_resets": 1,
          "resetter_combat_ratio": 90.24,
          "ts": "2026-05-21T10:57:47.667268+00:00"
        },
        {
          "combat_ratio": 61.54,
          "new_resets": 0,
          "resetter_combat_ratio": null,
          "ts": "2026-05-22T10:41:13.501310+00:00"
        },
        {
          "combat_ratio": 61.54,
          "new_resets": 0,
          "resetter_combat_ratio": null,
          "ts": "2026-05-23T09:42:45.900730+00:00"
        },
        {
          "combat_ratio": 61.54,
          "new_resets": 0,
          "resetter_combat_ratio": null,
          "ts": "2026-05-24T09:46:58.727404+00:00"
        },
        {
          "combat_ratio": 62.5,
          "new_resets": 0,
          "resetter_combat_ratio": null,
          "ts": "2026-05-25T11:41:51.179590+00:00"
        },
        {
          "combat_ratio": 51.56,
          "combat_resets": 0,
          "eco_resets": 0,
          "new_resets": 0,
          "resetter_combat_ratio": null,
          "ts": "2026-05-25T19:47:24.866422+00:00"
        },
        {
          "combat_ratio": 51.56,
          "combat_resets": 0,
          "eco_resets": 0,
          "new_resets": 0,
          "resetter_combat_ratio": null,
          "ts": "2026-05-25T20:25:27.342961+00:00"
        },
        {
          "combat_ratio": 51.56,
          "combat_resets": 0,
          "eco_resets": 0,
          "new_resets": 0,
          "resetter_combat_ratio": null,
          "ts": "2026-05-25T20:43:54.257477+00:00"
        }
      ],
      "known_veterans": [
        "686d5998b39f079a4a6ab8bd",
        "686222896c0e408991840f98",
        "6919ca3f8510e2692885fda6",
        "691a402bdb65494c1b646a40",
        "686fce41b8d1854d9d207c8e",
        "690420f04c4e3789a41cf68d",
        "6919387745ce8539d042fc98",
        "6932efe62ce8247c6c87cfcc",
        "692eeaa942d109428e54aaff",
        "696f5dadbea7a2698b4938a3",
        "698cc1b121c06469eeb6a9e2",
        "69974ca0b0a9df8277170755",
        "6996594553a5ede8f66adfe0",
        "683a88b98e35000e0108cbe8",
        "69bae5f81348cf457e2ace23",
        "69bc764ea9ceb0160dfb33e8",
        "69c6d3298a595e2dca9560aa",
        "69de13e25bb1f1ef9ff44eb7"
      ],
      "last_creep_alert": null,
      "last_creep_delta": null,
      "last_demob_alert": null,
      "last_demob_delta": null,
      "last_discovery": "2026-05-25T19:47:24.866422+00:00",
      "last_flagged_at": null,
      "last_flagged_peak_ratio": null,
      "last_urgent_alert": null,
      "last_urgent_count": null,
      "name": "Canada",
      "new_resets": 0,
      "resetter_combat_ratio": null,
      "sample_size": 18,
      "user_resets": {
        "686fce41b8d1854d9d207c8e": "2026-05-03T13:00:24.029Z",
        "690420f04c4e3789a41cf68d": "2026-05-21T16:58:27.995Z",
        "6919387745ce8539d042fc98": "2026-05-02T10:06:22.465Z",
        "6919ca3f8510e2692885fda6": "2026-05-15T21:14:38.846Z",
        "691a402bdb65494c1b646a40": "2026-05-11T13:33:37.904Z",
        "692eeaa942d109428e54aaff": "2026-05-18T01:17:34.963Z",
        "6932efe62ce8247c6c87cfcc": "2026-05-21T04:05:20.540Z",
        "696f5dadbea7a2698b4938a3": "2026-05-04T14:37:52.930Z",
        "6996594553a5ede8f66adfe0": "2026-05-02T14:52:38.688Z",
        "69bae5f81348cf457e2ace23": "2026-05-10T13:13:46.851Z",
        "69bc764ea9ceb0160dfb33e8": "2026-04-05T01:01:51.386Z",
        "69c6d3298a595e2dca9560aa": "2026-05-20T01:06:29.586Z"
      }
    },
    "6813b6d546e731854c7ac848": {
      "combat_ratio": 0.0,
      "combat_resets": 0,
      "eco_resets": 0,
      "history": [
        {
          "combat_ratio": 0.0,
          "new_resets": 0,
          "resetter_combat_ratio": null,
          "ts": "2026-05-19T10:53:00.828380+00:00"
        },
        {
          "combat_ratio": 0.0,
          "new_resets": 1,
          "resetter_combat_ratio": 0.0,
          "ts": "2026-05-20T10:41:03.855487+00:00"
        },
        {
          "combat_ratio": 0.0,
          "new_resets": 1,
          "resetter_combat_ratio": 97.22,
          "ts": "2026-05-21T10:57:47.667268+00:00"
        },
        {
          "combat_ratio": 0.0,
          "new_resets": 1,
          "resetter_combat_ratio": 0.0,
          "ts": "2026-05-22T10:41:13.501310+00:00"
        },
        {
          "combat_ratio": 0.0,
          "new_resets": 0,
          "resetter_combat_ratio": null,
          "ts": "2026-05-23T09:42:45.900730+00:00"
        },
        {
          "combat_ratio": 0.0,
          "new_resets": 0,
          "resetter_combat_ratio": null,
          "ts": "2026-05-24T09:46:58.727404+00:00"
        },
        {
          "combat_ratio": 0.0,
          "new_resets": 0,
          "resetter_combat_ratio": null,
          "ts": "2026-05-25T11:41:51.179590+00:00"
        },
        {
          "combat_ratio": 0.0,
          "combat_resets": 0,
          "eco_resets": 0,
          "new_resets": 0,
          "resetter_combat_ratio": null,
          "ts": "2026-05-25T19:47:24.866422+00:00"
        },
        {
          "combat_ratio": 0.0,
          "combat_resets": 0,
          "eco_resets": 0,
          "new_resets": 0,
          "resetter_combat_ratio": null,
          "ts": "2026-05-25T20:25:27.342961+00:00"
        },
        {
          "combat_ratio": 0.0,
          "combat_resets": 0,
          "eco_resets": 0,
          "new_resets": 0,
          "resetter_combat_ratio": null,
          "ts": "2026-05-25T20:43:54.257477+00:00"
        }
      ],
      "known_veterans": [
        "691b9ee792948e91cb1cffec",
        "6917de6050d80e15bcdb91f9",
        "69b933fe6843e2268ab37d0c",
        "69b84ea0ac25743c3fc8710b",
        "69b94d08caa5376ae5778a44",
        "69b99646feade6de9e1a9125",
        "69b875367ae3343efd514ae4",
        "69b83f587ae3343efdbcd85d",
        "69cfcfce7c951c1d66bced6b",
        "69d4158c6341955760edcd24",
        "691bb1a750d80e15bc06952b",
        "69d27ee27862e72e00400d4b",
        "69cc2ac5a1cf1b9306930f0b",
        "69dc26daf8d47c04e5390f51",
        "69e0d4efb6989dc2116ba37d",
        "69d4ee43e83deb4e60e151c0",
        "69d43d5c2e2a33a2ae5b912d",
        "69d7c5cdf5419ebd5ba66559",
        "69c3c59e68a97bd50e031381"
      ],
      "last_creep_alert": null,
      "last_creep_delta": null,
      "last_demob_alert": null,
      "last_demob_delta": null,
      "last_discovery": "2026-05-25T19:47:24.866422+00:00",
      "last_flagged_at": null,
      "last_flagged_peak_ratio": null,
      "last_urgent_alert": null,
      "last_urgent_count": null,
      "name": "Morocco",
      "new_resets": 0,
      "resetter_combat_ratio": null,
      "sample_size": 19,
      "user_resets": {
        "6917de6050d80e15bcdb91f9": "2026-05-20T23:10:12.768Z",
        "691b9ee792948e91cb1cffec": "2026-05-19T12:55:48.878Z",
        "691bb1a750d80e15bc06952b": "2026-05-03T04:19:44.445Z",
        "69b83f587ae3343efdbcd85d": "2026-05-07T22:31:02.609Z",
        "69b84ea0ac25743c3fc8710b": "2026-04-29T11:07:26.771Z",
        "69b875367ae3343efd514ae4": "2026-05-21T22:03:05.765Z",
        "69b933fe6843e2268ab37d0c": "2026-05-19T07:16:17.386Z",
        "69b94d08caa5376ae5778a44": "2026-05-15T23:56:46.706Z",
        "69b99646feade6de9e1a9125": "2026-05-07T09:27:23.628Z",
        "69c3c59e68a97bd50e031381": "2026-04-22T16:31:48.033Z",
        "69cc2ac5a1cf1b9306930f0b": "2026-05-18T17:53:27.427Z",
        "69cfcfce7c951c1d66bced6b": "2026-04-21T21:35:17.186Z",
        "69d27ee27862e72e00400d4b": "2026-04-23T14:15:26.252Z",
        "69d4158c6341955760edcd24": "2026-05-15T13:21:35.253Z",
        "69d43d5c2e2a33a2ae5b912d": "2026-05-11T10:51:24.629Z",
        "69d4ee43e83deb4e60e151c0": "2026-05-12T17:23:52.194Z",
        "69d7c5cdf5419ebd5ba66559": "2026-05-05T23:04:44.182Z",
        "69dc26daf8d47c04e5390f51": "2026-05-06T21:05:31.579Z",
        "69e0d4efb6989dc2116ba37d": "2026-04-19T22:02:52.276Z"
      }
    },
    "6813b6d546e731854c7ac84e": {
      "combat_ratio": 0.0,
      "combat_resets": 0,
      "eco_resets": 0,
      "history": [
        {
          "combat_ratio": 0.0,
          "new_resets": 0,
          "resetter_combat_ratio": null,
          "ts": "2026-05-19T10:53:00.828380+00:00"
        },
        {
          "combat_ratio": 0.0,
          "new_resets": 0,
          "resetter_combat_ratio": null,
          "ts": "2026-05-20T10:41:03.855487+00:00"
        },
        {
          "combat_ratio": 0.0,
          "new_resets": 1,
          "resetter_combat_ratio": 0.0,
          "ts": "2026-05-21T10:57:47.667268+00:00"
        },
        {
          "combat_ratio": 0.0,
          "new_resets": 2,
          "resetter_combat_ratio": 48.41,
          "ts": "2026-05-22T10:41:13.501310+00:00"
        },
        {
          "combat_ratio": 0.0,
          "new_resets": 0,
          "resetter_combat_ratio": null,
          "ts": "2026-05-23T09:42:45.900730+00:00"
        },
        {
          "combat_ratio": 0.0,
          "new_resets": 1,
          "resetter_combat_ratio": 0.0,
          "ts": "2026-05-24T09:46:58.727404+00:00"
        },
        {
          "combat_ratio": 0.0,
          "new_resets": 2,
          "resetter_combat_ratio": 42.11,
          "ts": "2026-05-25T11:41:51.179590+00:00"
        },
        {
          "combat_ratio": 0.0,
          "combat_resets": 0,
          "eco_resets": 0,
          "new_resets": 0,
          "resetter_combat_ratio": null,
          "ts": "2026-05-25T19:47:24.866422+00:00"
        },
        {
          "combat_ratio": 0.0,
          "combat_resets": 0,
          "eco_resets": 0,
          "new_resets": 0,
          "resetter_combat_ratio": null,
          "ts": "2026-05-25T20:25:27.342961+00:00"
        },
        {
          "combat_ratio": 0.0,
          "combat_resets": 0,
          "eco_resets": 0,
          "new_resets": 0,
          "resetter_combat_ratio": null,
          "ts": "2026-05-25T20:43:54.257477+00:00"
        }
      ],
      "known_veterans": [
        "6999a9d29e864b6c118b8048",
        "69b76ebe95d04b39a3984ba0",
        "69c7bb89c1a06d6b1eb6b832",
        "69ceafe8f6e3d77336c6e789",
        "69cd7fe6d3c41fea89e78ebc",
        "69d7d51fabd1bf8c1ff950f3",
        "69d044f35098cc20271e21d0",
        "69d028158c2824b1034594f0",
        "69d1151d78e94f288e61780a",
        "69d2a8a2c957f80717156eaf",
        "69d027e0e3889832aea1dd41",
        "69d82709e86a67f8f6c9ea77",
        "69d7f27492e0a751daa3879d",
        "69e0a6e74e15eeb2990b0852",
        "69d8e53dd6d9b31f49752860"
      ],
      "last_creep_alert": null,
      "last_creep_delta": null,
      "last_demob_alert": null,
      "last_demob_delta": null,
      "last_discovery": "2026-05-25T19:47:24.866422+00:00",
      "last_flagged_at": null,
      "last_flagged_peak_ratio": null,
      "last_urgent_alert": null,
      "last_urgent_count": null,
      "name": "Tunisia",
      "new_resets": 0,
      "resetter_combat_ratio": null,
      "sample_size": 15,
      "user_resets": {
        "6999a9d29e864b6c118b8048": "2026-05-24T10:48:11.892Z",
        "69b76ebe95d04b39a3984ba0": "2026-05-16T01:42:27.214Z",
        "69c7bb89c1a06d6b1eb6b832": "2026-05-21T19:40:08.198Z",
        "69cd7fe6d3c41fea89e78ebc": "2026-04-15T13:44:36.632Z",
        "69ceafe8f6e3d77336c6e789": "2026-05-24T23:37:02.389Z",
        "69d027e0e3889832aea1dd41": "2026-05-20T21:10:45.865Z",
        "69d028158c2824b1034594f0": "2026-05-24T13:53:47.083Z",
        "69d044f35098cc20271e21d0": "2026-05-14T18:56:30.179Z",
        "69d1151d78e94f288e61780a": "2026-05-16T15:03:02.639Z",
        "69d2a8a2c957f80717156eaf": "2026-05-22T01:35:32.088Z",
        "69d7d51fabd1bf8c1ff950f3": "2026-05-24T00:12:12.895Z",
        "69d7f27492e0a751daa3879d": "2026-05-20T18:21:04.638Z",
        "69d82709e86a67f8f6c9ea77": "2026-05-03T15:22:26.826Z",
        "69d8e53dd6d9b31f49752860": "2026-05-19T20:08:34.854Z",
        "69e0a6e74e15eeb2990b0852": "2026-04-30T17:37:08.471Z"
      }
    },
    "6813b6d546e731854c7ac858": {
      "combat_ratio": 84.21,
      "combat_resets": 0,
      "eco_resets": 0,
      "known_veterans": [
        "69a45b3221a5cf92d89285e3",
        "69a19f15ec91a7019f18f687",
        "699fbbc5c93cbbf890f17e91",
        "699f760736961394b8b7023c",
        "699f097c334c0732477d6790",
        "699e632319024e8057b1d1f7",
        "699e161a30100a1fd64f38a6",
        "699df1de30100a1fd6f83955",
        "699d0c4031b67b4758360a4e",
        "699d067ba31a7b4b2a83c81f",
        "699cdea8e398704ab06890ab",
        "699cf848a7fd8a4e27333003",
        "699cdf2b657b9604439ae537",
        "699ca99ed321d631c318bfa0",
        "699c9969b232a1efde0c9924",
        "699cb17ba5d3feeeb39e1690",
        "699bde77cbc612c0385f7816",
        "69a9c1dc98c1c2c3d031eec3",
        "69a5097b7eba1f779b76891a",
        "699fed0ec93cbbf8901aa3ed",
        "699fa0639a0b8b207792a3d2",
        "699f519e6ff9e995cf7f5427",
        "699e5da419024e8057ab5edc",
        "699e103ed70af7f975395e09",
        "699d9676d8ed65cda99b7a95"
      ],
      "last_creep_alert": null,
      "last_creep_delta": null,
      "last_demob_alert": null,
      "last_demob_delta": null,
      "last_discovery": "2026-05-18T12:44:56.790190+00:00",
      "last_flagged_at": null,
      "last_flagged_peak_ratio": null,
      "last_urgent_alert": null,
      "last_urgent_count": null,
      "name": "Venezuela",
      "sample_size": 25,
      "user_resets": {}
    },
    "6813b6d546e731854c7ac8a0": {
      "combat_ratio": 2.5,
      "combat_resets": 0,
      "eco_resets": 0,
      "history": [
        {
          "combat_ratio": 0.0,
          "new_resets": 0,
          "resetter_combat_ratio": null,
          "ts": "2026-05-19T10:53:00.828380+00:00"
        },
        {
          "combat_ratio": 0.0,
          "new_resets": 0,
          "resetter_combat_ratio": null,
          "ts": "2026-05-20T10:41:03.855487+00:00"
        },
        {
          "combat_ratio": 2.5,
          "new_resets": 2,
          "resetter_combat_ratio": 46.34,
          "ts": "2026-05-21T10:57:47.667268+00:00"
        },
        {
          "combat_ratio": 2.5,
          "new_resets": 0,
          "resetter_combat_ratio": null,
          "ts": "2026-05-22T10:41:13.501310+00:00"
        },
        {
          "combat_ratio": 2.5,
          "new_resets": 0,
          "resetter_combat_ratio": null,
          "ts": "2026-05-23T09:42:45.900730+00:00"
        },
        {
          "combat_ratio": 2.5,
          "new_resets": 0,
          "resetter_combat_ratio": null,
          "ts": "2026-05-24T09:46:58.727404+00:00"
        },
        {
          "combat_ratio": 2.5,
          "new_resets": 0,
          "resetter_combat_ratio": null,
          "ts": "2026-05-25T11:41:51.179590+00:00"
        }
      ],
      "known_veterans": [
        "696015fb3ba7d31c06bb134e",
        "697508c6140a977301a77ff3",
        "69a0306fbb9514d251956de2",
        "69a67eff2cde27ace9bb0727",
        "69a9cd9c72c4f3a3b46fd718",
        "69a822c9c1a99b8fc588a180",
        "69a4931543fa074c9cb9886f",
        "69b0f297445e36e40589ebf2",
        "69b849dfca9a42b7ef8c8d27",
        "69bb25c866cd74073340eb81",
        "69ce929b2315278ee68836d0",
        "69d42e332a7ca57f06880a33"
      ],
      "last_creep_alert": null,
      "last_creep_delta": null,
      "last_demob_alert": null,
      "last_demob_delta": null,
      "last_discovery": "2026-05-19T10:53:00.828380+00:00",
      "last_flagged_at": null,
      "last_flagged_peak_ratio": null,
      "last_urgent_alert": null,
      "last_urgent_count": null,
      "name": "Suriname",
      "new_resets": 0,
      "resetter_combat_ratio": null,
      "sample_size": 12,
      "user_resets": {
        "696015fb3ba7d31c06bb134e": "2026-05-15T05:32:12.640Z",
        "697508c6140a977301a77ff3": "2026-05-20T21:10:32.491Z",
        "69a0306fbb9514d251956de2": "2026-04-26T19:29:11.242Z",
        "69a4931543fa074c9cb9886f": "2026-05-03T11:18:14.048Z",
        "69a67eff2cde27ace9bb0727": "2026-05-17T20:09:25.177Z",
        "69a822c9c1a99b8fc588a180": "2026-05-21T06:42:34.377Z",
        "69b0f297445e36e40589ebf2": "2026-05-12T14:04:39.465Z",
        "69b849dfca9a42b7ef8c8d27": "2026-05-12T17:52:44.018Z",
        "69bb25c866cd74073340eb81": "2026-05-18T16:22:35.141Z",
        "69ce929b2315278ee68836d0": "2026-05-17T22:58:53.019Z"
      }
    },
    "683ddd2c24b5a2e114af15c5": {
      "combat_ratio": 6.9,
      "combat_resets": 0,
      "eco_resets": 0,
      "history": [
        {
          "combat_ratio": 0.0,
          "new_resets": 0,
          "resetter_combat_ratio": null,
          "ts": "2026-05-19T10:53:00.828380+00:00"
        },
        {
          "combat_ratio": 0.0,
          "new_resets": 0,
          "resetter_combat_ratio": null,
          "ts": "2026-05-20T10:41:03.855487+00:00"
        },
        {
          "combat_ratio": 0.0,
          "new_resets": 0,
          "resetter_combat_ratio": null,
          "ts": "2026-05-21T10:57:47.667268+00:00"
        },
        {
          "combat_ratio": 0.0,
          "new_resets": 0,
          "resetter_combat_ratio": null,
          "ts": "2026-05-22T10:41:13.501310+00:00"
        },
        {
          "combat_ratio": 0.0,
          "new_resets": 0,
          "resetter_combat_ratio": null,
          "ts": "2026-05-23T09:42:45.900730+00:00"
        },
        {
          "combat_ratio": 0.0,
          "new_resets": 0,
          "resetter_combat_ratio": null,
          "ts": "2026-05-24T09:46:58.727404+00:00"
        },
        {
          "combat_ratio": 6.9,
          "new_resets": 1,
          "resetter_combat_ratio": 90.0,
          "ts": "2026-05-25T11:41:51.179590+00:00"
        },
        {
          "combat_ratio": 6.9,
          "combat_resets": 0,
          "eco_resets": 0,
          "new_resets": 0,
          "resetter_combat_ratio": null,
          "ts": "2026-05-25T19:47:24.866422+00:00"
        },
        {
          "combat_ratio": 6.9,
          "combat_resets": 0,
          "eco_resets": 0,
          "new_resets": 0,
          "resetter_combat_ratio": null,
          "ts": "2026-05-25T20:25:27.342961+00:00"
        },
        {
          "combat_ratio": 6.9,
          "combat_resets": 0,
          "eco_resets": 0,
          "new_resets": 0,
          "resetter_combat_ratio": null,
          "ts": "2026-05-25T20:43:54.257477+00:00"
        }
      ],
      "known_veterans": [
        "6818f900286675c678920eea",
        "68299b85e10d9906654ce2ec",
        "6820e463d7b95c3c75c20727",
        "6878df0adb897ec4d58bf9cd",
        "68970cf04fad0d6e36b2f310",
        "68f50c56dd4b0abd5938c1cf",
        "69150c494e48e9d359ce054c",
        "6914c6cfdf870cbb88a088c4",
        "682085d9d6fa1e7f1606ebcb",
        "6955be14b1fc6d0b7bfde964",
        "69c3fa526853ceaa7a149222",
        "698b537def0c6320c861c3f2",
        "69d161d6904e27bdeea39cf7"
      ],
      "last_creep_alert": null,
      "last_creep_delta": null,
      "last_demob_alert": null,
      "last_demob_delta": null,
      "last_discovery": "2026-05-25T19:47:24.866422+00:00",
      "last_flagged_at": null,
      "last_flagged_peak_ratio": null,
      "last_urgent_alert": null,
      "last_urgent_count": null,
      "name": "Iceland",
      "new_resets": 0,
      "resetter_combat_ratio": null,
      "sample_size": 13,
      "user_resets": {
        "6818f900286675c678920eea": "2026-05-12T15:09:02.543Z",
        "682085d9d6fa1e7f1606ebcb": "2026-04-01T04:52:18.545Z",
        "6820e463d7b95c3c75c20727": "2026-05-06T17:52:44.112Z",
        "6878df0adb897ec4d58bf9cd": "2026-05-13T08:21:21.036Z",
        "68f50c56dd4b0abd5938c1cf": "2026-05-07T04:02:11.699Z",
        "6914c6cfdf870cbb88a088c4": "2026-04-19T09:50:04.421Z",
        "69150c494e48e9d359ce054c": "2026-05-15T12:37:44.265Z",
        "6955be14b1fc6d0b7bfde964": "2026-05-16T20:46:20.262Z",
        "69c3fa526853ceaa7a149222": "2026-04-19T05:07:08.960Z",
        "69d161d6904e27bdeea39cf7": "2026-05-05T16:08:33.572Z"
      }
    }
  },
  "flagged_last_run": [],
  "last_run": "2026-05-25T20:43:54.257477+00:00",
  "version": 6
}
